mango_test/__init__.py
mango_test/mango_test.py
mango_coding_test_pl_sept20-2.0.0.dist-info/METADATA
mango_coding_test_pl_sept20-2.0.0.dist-info/WHEEL
mango_coding_test_pl_sept20-2.0.0.dist-info/top_level.txt
mango_coding_test_pl_sept20-2.0.0.dist-info/RECORD
