Metadata-Version: 2.1
Name: mango-coding-test-pl-sept20
Version: 2.0.0
Summary: Solutions to Mango's Python Coding Test
Home-page: UNKNOWN
Author: UNKNOWN
Author-email: UNKNOWN
License: UNKNOWN
Platform: UNKNOWN
Requires-Dist: numpy
